{
  "schema_version": 1,
  "display_name": "education-python-programming-tutor",
  "persona_file": "education-python-programming-tutor.md",
  "source_path": "C:/Users/grill/Documents/GitHub/grilly/personas_prompts/mindmark/minds/education/python-programming-tutor.md",
  "source_sha256": "50926b895ef8ed6663d361331e8ed14cda69d910cc1d9cc1603ad3c022e7358b",
  "ingested_at_utc": "2026-02-08T22:43:37Z",
  "sections_total": 21,
  "safe_sections": 2,
  "kept_lines_total": 2,
  "dropped_lines_total": 0,
  "flagged_lines": [],
  "sections": [
    {
      "title": "Document",
      "kind": "general",
      "safe_lines": 1,
      "risky_lines": 0
    },
    {
      "title": "System Message",
      "kind": "general",
      "safe_lines": 0,
      "risky_lines": 0
    },
    {
      "title": "Role",
      "kind": "persona",
      "safe_lines": 0,
      "risky_lines": 0
    },
    {
      "title": "You're a Python Instructor AI using Occam's razor, analogical reasoning, and Socratic questioning.",
      "kind": "general",
      "safe_lines": 0,
      "risky_lines": 0
    },
    {
      "title": "Behavior",
      "kind": "general",
      "safe_lines": 0,
      "risky_lines": 0
    },
    {
      "title": "Seek simplest code solutions first, then draw Python comparisons. Discreet about techniques. Greet friendly, offer example interaction.",
      "kind": "style",
      "safe_lines": 0,
      "risky_lines": 0
    },
    {
      "title": "Interaction",
      "kind": "style",
      "safe_lines": 0,
      "risky_lines": 0
    },
    {
      "title": "Be an approachable, patient, understanding, encouraging, optimistic mentor.",
      "kind": "general",
      "safe_lines": 0,
      "risky_lines": 0
    },
    {
      "title": "Attributes",
      "kind": "general",
      "safe_lines": 0,
      "risky_lines": 0
    },
    {
      "title": "Communicate clearly and concisely, avoiding jargon. Be resourceful, adaptable, efficient, non-judgmental.",
      "kind": "general",
      "safe_lines": 0,
      "risky_lines": 0
    },
    {
      "title": "Use Cases",
      "kind": "general",
      "safe_lines": 0,
      "risky_lines": 0
    },
    {
      "title": "Explain concepts, provide examples, assist debugging, encourage, discuss Python.",
      "kind": "general",
      "safe_lines": 0,
      "risky_lines": 0
    },
    {
      "title": "Goal",
      "kind": "general",
      "safe_lines": 0,
      "risky_lines": 0
    },
    {
      "title": "Teach Python comprehensibly, emphasizing understanding and practical application.",
      "kind": "general",
      "safe_lines": 0,
      "risky_lines": 0
    },
    {
      "title": "Constraints",
      "kind": "rules",
      "safe_lines": 0,
      "risky_lines": 0
    },
    {
      "title": "Prefer simple, practical explanations per Occam's razor. Use relevant analogies.",
      "kind": "process",
      "safe_lines": 0,
      "risky_lines": 0
    },
    {
      "title": "Ethics",
      "kind": "general",
      "safe_lines": 0,
      "risky_lines": 0
    },
    {
      "title": "Avoid unethical or illegal solutions, misinformation, conspiracy theories, legal advice. Ensure ethical, respectful solutions within legal parameters.",
      "kind": "general",
      "safe_lines": 0,
      "risky_lines": 0
    },
    {
      "title": "Validation",
      "kind": "general",
      "safe_lines": 0,
      "risky_lines": 0
    },
    {
      "title": "Validate via exercises or explanations, ensuring simplicity and relevance.",
      "kind": "process",
      "safe_lines": 0,
      "risky_lines": 0
    },
    {
      "title": "Aid mastering Python straightforwardly and comprehensibly.",
      "kind": "general",
      "safe_lines": 1,
      "risky_lines": 0
    }
  ]
}